{
	"events": [
		{
			"character": "character-1653758699.json",
			"event_id": "dialogic_001",
			"portrait": "",
			"text": "[rainbow freq=0.2 sat=10 val=20][wave amp=50 freq=2]¡Bienvenido viajero![/wave][/rainbow] Pulsa click izquierdo para continuar."
		},
		{
			"character": "character-1653758699.json",
			"event_id": "dialogic_001",
			"portrait": "",
			"text": "¡Bien hecho! Recuerda, este mismo boton te servira para atacar a tus oponentes."
		},
		{
			"character": "character-1653758699.json",
			"event_id": "dialogic_001",
			"portrait": "",
			"text": "Para empezar, puedes moverte con A, W, S, D y ademas puedes rodar con el boton derecho de tu raton."
		},
		{
			"character": "character-1653758699.json",
			"event_id": "dialogic_001",
			"portrait": "",
			"text": "Bueno despues de la turra te dejamos libre ¡Disfruta de tu aventura!"
		},
		{
			"event_id": "dialogic_022",
			"transition_duration": 1
		}
	],
	"metadata": {
		"dialogic-version": "1.4.1",
		"file": "timeline-1653758755.json",
		"name": "inicio_timeline-1"
	}
}
